{
 "align_labels_right": 0,
 "creation": "2021-11-22 13:33:25.306824",
 "css": "",
 "custom_format": 1,
 "default_print_language": "en",
 "disabled": 0,
 "doc_type": "Sales Order",
 "docstatus": 0,
 "doctype": "Print Format",
 "font": "Default",
 "format_data": "[{\"fieldname\": \"print_heading_template\", \"fieldtype\": \"Custom HTML\", \"options\": \"<div class=\\\"print-heading\\\" style=\\\"border-bottom: None; margin-bottom: 0px; padding-bottom: 0px;\\\">\\n    <h2>Sales Order<br></h2>\\n    {{ get_barcode(doc.name) }} <br>\\n    {% if doc.company_address %}\\n        <div style=\\\"text-align: left;\\\">\\n            {% set address = frappe.get_doc('Address', doc.company_address) %}\\n            {{ address.ifw_first_name }} <br>\\n            {{address.address_line1}}\\n            {% if address.address_line2 %}\\n                . {{address.address_line2}}\\n            {% endif %}\\n            , {{address.city}}, {{address.pincode}}, {{address.country}}\\n        </div>\\n    {% endif %}\\n</div>\"}, {\"fieldtype\": \"Section Break\", \"label\": \"\"}, {\"fieldtype\": \"Column Break\"}, {\"fieldname\": \"_custom_html\", \"print_hide\": 0, \"label\": \"Custom HTML\", \"fieldtype\": \"HTML\", \"options\": \"<b>ORDER DATE:</b><br>\\n{{doc.transaction_date}}\"}, {\"fieldtype\": \"Column Break\"}, {\"fieldname\": \"_custom_html\", \"print_hide\": 0, \"label\": \"Custom HTML\", \"fieldtype\": \"HTML\", \"options\": \"<div style=\\\"width: 33%; float: left;\\\">\\n    <b>Customer PO#:</b><br>\\n    {{doc.po_no}}\\n</div>\\n<div style=\\\"width: 33%; float: left;\\\">\\n    <b>Customer #:</b><br>\\n    Customer No\\n</div>\\n<div style=\\\"width: 33%; float: left;\\\">\\n    <b>Order#:</b><br>\\n    {{doc.po_no}}\\n</div>\"}, {\"fieldtype\": \"Section Break\", \"label\": \"Address and Contact\"}, {\"fieldtype\": \"Column Break\"}, {\"fieldname\": \"_custom_html\", \"print_hide\": 0, \"label\": \"Custom HTML\", \"fieldtype\": \"HTML\", \"options\": \"<div style=\\\"width: 50%; float: left; margin-top: 10px;\\\">\\n    <b>BILL TO:</b><br>\\n    {{doc.customer}} <br>\\n    {% if doc.customer_address %}\\n        {% set address = frappe.get_doc('Address', doc.customer_address) %}\\n        {{address.address_line1}} <br>\\n        {% if address.address_line2 %}\\n            {{address.address_line2}} <br>\\n        {% endif %}\\n        {{ address.city }}, {{ address.state }}\\n        {{address.pincode}} <br>\\n        {{address.country}}\\n    {% endif %}\\n</div>\\n<div style=\\\"width: 50%; float: left; margin-top: 10px;\\\">\\n    <b>SHIP TO:</b><br>\\n    {{doc.customer}} <br>\\n    {% if doc.shipping_address_name %}\\n        {% set address = frappe.get_doc('Address', doc.shipping_address_name) %}\\n        {{address.address_line1}} <br>\\n        {% if address.address_line2 %}\\n            {{address.address_line2}} <br>\\n        {% endif %}\\n        {{ address.city }}, {{ address.state }}\\n        {{address.pincode}} <br>\\n        {{address.country}}\\n    {% elif doc.customer_address%}\\n        {% set address = frappe.get_doc('Address', doc.customer_address) %}\\n        {{address.address_line1}} <br>\\n        {% if address.address_line2 %}\\n            {{address.address_line2}} <br>\\n        {% endif %}\\n        {{ address.city }}, {{ address.state }}\\n        {{address.pincode}} <br>\\n        {{address.country}}\\n    {% endif %}\\n</div>\"}, {\"fieldtype\": \"Column Break\"}, {\"fieldname\": \"_custom_html\", \"print_hide\": 0, \"label\": \"Custom HTML\", \"fieldtype\": \"HTML\", \"options\": \"<div style=\\\"margin-top: 10px;\\\">\\n    <b>COMMENTS / SHIPPING INSTRUCTIONS:</b><br>\\n    {% if doc.ifw_online_order_comments %}\\n        {{ doc.ifw_online_order_comments }}\\n    {% endif %}\\n</div>\"}, {\"fieldtype\": \"Section Break\", \"label\": \"\"}, {\"fieldtype\": \"Column Break\"}, {\"fieldname\": \"_custom_html\", \"print_hide\": 0, \"label\": \"Custom HTML\", \"fieldtype\": \"HTML\", \"options\": \"<div style=\\\"margin-top: 10px;\\\">\\n<b>Contact:</b><br>\\n{% if doc.contact_person %}\\n    {% set email = frappe.db.get_value('Contact', doc.contact_person, \\\"email_id\\\") %}\\n    {% if email %}\\n        {{email}} <br>\\n    {% endif %}\\n    {% set phone = frappe.db.get_value('Contact', doc.contact_person, \\\"phone\\\") %}\\n    {% if phone %}\\n        {{phone}}\\n    {% endif %}\\n{% elif doc.customer_address %}\\n    {% set address = frappe.get_doc('Address', doc.customer_address) %}\\n    {% if address.email_id %}\\n        {{address.email_id}} <br>\\n    {% endif %}\\n    {% if address.phone %}\\n        {{address.phone}}\\n    {% endif %}\\n{% endif%}\\n</div>\"}, {\"fieldtype\": \"Column Break\"}, {\"fieldtype\": \"Section Break\", \"label\": \"\"}, {\"fieldtype\": \"Column Break\"}, {\"fieldname\": \"_custom_html\", \"print_hide\": 0, \"label\": \"Custom HTML\", \"fieldtype\": \"HTML\", \"options\": \"<table class=\\\"table table-condensed cart no-border\\\" style=\\\"font-size:100%;margin-top: 10px;\\\">\\n\\t<colgroup>\\n\\t\\t<col style=\\\"width:5% ; height: auto;\\\">\\n\\t\\t<col style=\\\"width:25%\\\">\\n\\t\\t<col style=\\\"width:20%\\\">\\n\\t\\t<col style=\\\"width:10%\\\">\\n\\t\\t<col style=\\\"width:07%\\\">\\n\\t</colgroup>\\n\\n\\t<tr>\\n\\t\\t<th class =\\\"text-center\\\" style = \\\"border-top:1px solid #D3D3D3;border-left:1px solid #D3D3D3!important;border-right:1px solid #D3D3D3!important;border-bottom:1px solid #D3D3D3!important;padding:1px!important;\\\">SKU</th>\\n\\t\\t<th class =\\\"text-center\\\" style = \\\"border-top:1px solid #D3D3D3;border-left:1px solid #D3D3D3!important;border-right:1px solid #D3D3D3!important;border-bottom:1px solid #D3D3D3!important;padding:1px!important;\\\">Item Name</th>\\n\\t\\t<th class =\\\"text-center\\\" style = \\\"border-top:1px solid #D3D3D3;border-left:1px solid #D3D3D3!important;border-right:1px solid #D3D3D3!important;border-bottom:1px solid #D3D3D3!important;padding:1px!important;\\\">Qty</th>\\n\\t\\t<th class =\\\"text-center\\\" style = \\\"border-top:1px solid #D3D3D3;border-left:1px solid #D3D3D3!important;border-right:1px solid #D3D3D3!important;border-bottom:1px solid #D3D3D3!important;padding:1px!important;\\\">Unit</th>\\n\\t\\t<th class =\\\"text-center\\\" style = \\\"border-top:1px solid #D3D3D3;border-left:1px solid #D3D3D3!important;border-right:1px solid #D3D3D3!important;border-bottom:1px solid #D3D3D3!important;padding:1px!important;\\\">Extension</th>\\n\\t</tr>\\n\\n\\t{% for item in doc.items %}\\n\\t<tr>\\n\\t\\t<td class =\\\"text-center\\\" style = \\\"border-top:1px solid!important;border-left:1px solid #D3D3D3!important;border-right:1px solid #D3D3D3!important;border-bottom:1px solid #D3D3D3!important;padding:1px!important;\\\">\\n\\t        {% if item.ifw_retailskusuffix %}\\n\\t            {{ item.ifw_retailskusuffix }}\\n\\t        {% endif %}\\n\\t    </td>\\n\\t\\t<td class =\\\"text-center\\\" style = \\\"border-top:1px solid!important;border-left:1px solid #D3D3D3!important;border-right:1px solid #D3D3D3!important;border-bottom:1px solid #D3D3D3!important;padding:1px!important;\\\"> \\n\\t\\t\\t{{ item.item_name }}\\n\\t\\t</td>\\n\\t\\t<td class =\\\"text-center\\\" style = \\\"border-top:1px solid!important;border-left:1px solid #D3D3D3!important;border-right:1px solid #D3D3D3!important;border-bottom:1px solid #D3D3D3!important;padding:1px!important;\\\"> \\n\\t\\t\\t{{ item.qty }} \\n\\t\\t</td>\\n\\t\\t<td class =\\\"text-center\\\" style = \\\"border-top:1px solid!important;border-left:1px solid #D3D3D3!important;border-right:1px solid #D3D3D3!important;border-bottom:1px solid #D3D3D3!important;padding:1px!important;\\\"> \\n\\t\\t\\t{{ item.rate }}\\n\\t\\t</td>\\n\\t\\t<td class =\\\"text-center\\\" style = \\\"border-top:1px solid!important;border-left:1px solid #D3D3D3!important;border-right:1px solid #D3D3D3!important;border-bottom:1px solid #D3D3D3!important;padding:1px!important;\\\"> \\n\\t\\t\\t{{ item.amount }} \\n\\t\\t</td>\\n\\t</tr>\\n\\n\\n\\t{% endfor %}\\n</table>\"}, {\"fieldtype\": \"Section Break\", \"label\": \"\"}, {\"fieldtype\": \"Column Break\"}, {\"fieldname\": \"_custom_html\", \"print_hide\": 0, \"label\": \"Custom HTML\", \"fieldtype\": \"HTML\", \"options\": \"<b>* ALL PRICES IN {{doc.currency}}</b>\"}, {\"fieldtype\": \"Column Break\"}, {\"fieldname\": \"_custom_html\", \"print_hide\": 0, \"label\": \"Custom HTML\", \"fieldtype\": \"HTML\", \"options\": \"<div style=\\\"border: solid 1px #dfe2e5; padding: 10px 0px;\\\">\\n    <table style=\\\"width: 100%;\\\">\\n        <tr>\\n            <td style=\\\"width: 50%; text-align: right;\\\"><b>SUBTOTAL</b></td>\\n            <td style=\\\"width: 50%;\\\"><b>$ {{doc.total}}</b></td>\\n        </tr>\\n        {% for tax in doc.taxes %}\\n            <tr>\\n                <td style=\\\"width: 50%; text-align: right;\\\"><b>{{ tax.description }}</b></td>\\n                <td style=\\\"width: 50%;\\\"><b>$ {{ tax.tax_amount }}<b></td>\\n            </tr>\\n        {% endfor %}\\n        <tr>\\n            <td style=\\\"width: 50%; text-align: right;\\\"><b>TOTAL</b></td>\\n            <td style=\\\"width: 50%;\\\"><b>$ {{doc.grand_total}}</b></td>\\n        </tr>\\n    </table>\\n</div>\"}, {\"fieldtype\": \"Section Break\", \"label\": \"Terms and Conditions\"}, {\"fieldtype\": \"Column Break\"}, {\"fieldname\": \"_custom_html\", \"print_hide\": 0, \"label\": \"Custom HTML\", \"fieldtype\": \"HTML\", \"options\": \"<div id=\\\"footer-html\\\">\\n\\t{% if doc.terms %}\\n\\t    <div class=\\\"letter-head-footer\\\">\\n\\t\\t\\t<span>{{doc.terms}}</span>\\n\\t\\t</div>\\n    {% endif %}\\n\\t<p class=\\\"text-center small page-number visible-pdf\\\">\\n\\t\\t{{ _(\\\"Page {0} of {1}\\\").format('<span class=\\\"page\\\"></span>', '<span class=\\\"topage\\\"></span>') }}\\n\\t</p>\\n</div>\\n\"}]",
 "html": "<div style=\"width: 100%\">\n    <div style=\"width: 100%; text-align: right; float: left;\">\n        <div style=\"width: 50%; float: right;\">\n            <h2 style=\"margin-bottom: 0px; font-size: 24px; color: #666;\">SALES ORDER<br></h2>\n            {{ get_barcode(doc.name) }} <br>\n            {% if doc.company_address %}\n                <div>\n                    {% set address = frappe.get_doc('Address', doc.company_address) %}\n                    {{ address.ifw_first_name }} <br>\n                    {{address.address_line1}}\n                    {% if address.address_line2 %}\n                        . {{address.address_line2}}\n                    {% endif %}\n                    , {{address.city}}, {{address.pincode}}, {{address.country}}\n                </div>\n            {% endif %}\n        </div>\n    </div>\n    <div style=\"width: 100%; float: left; margin-top: 15px;\">\n        <div style=\"width: 50%; float: left;\">\n            <b>ORDER DATE:</b><br>\n            {{frappe.utils.get_datetime(doc.transaction_date).strftime('%d-%b-%Y')}}\n        </div>\n        <div style=\"width: 25%; float: left;\">\n            <b>Customer PO#:</b><br>\n            {% if doc.po_no %}\n                {{doc.po_no}}\n            {% endif %}\n        </div>\n        <div style=\"width: 25%; float: left;\">\n            <b>Order#:</b><br>\n            {{doc.name.strip('SAL-ORD-')}}\n        </div>\n    </div>\n    <div style=\"width: 100%; float: left; margin-top: 15px;\">\n        <div style=\"width: 25%; float: left;\">\n            <b>BILL TO:</b><br>\n            {{doc.customer}} <br>\n            {% if doc.customer_address %}\n                {% set address = frappe.get_doc('Address', doc.customer_address) %}\n                {{address.address_line1}} <br>\n                {% if address.address_line2 %}\n                    {{address.address_line2}} <br>\n                {% endif %}\n                {{ address.city }}, {{ address.state }}<br>\n                {{address.pincode}} <br>\n                {{address.country}}\n            {% endif %}\n        </div>\n        <div style=\"width: 25%; float: left; padding-left: 5px;\">\n            <b>SHIP TO:</b><br>\n            {{doc.customer}} <br>\n            {% if doc.shipping_address_name %}\n                {% set address = frappe.get_doc('Address', doc.shipping_address_name) %}\n                {{address.address_line1}} <br>\n                {% if address.address_line2 %}\n                    {{address.address_line2}} <br>\n                {% endif %}\n                {{ address.city }}, {{ address.state }}<br>\n                {{address.pincode}} <br>\n                {{address.country}}\n            {% elif doc.customer_address%}\n                {% set address = frappe.get_doc('Address', doc.customer_address) %}\n                {{address.address_line1}} <br>\n                {% if address.address_line2 %}\n                    {{address.address_line2}} <br>\n                {% endif %}\n                {{ address.city }}, {{ address.state }}<br>\n                {{address.pincode}} <br>\n                {{address.country}}\n            {% endif %}\n        </div>\n        <div style=\"width: 50%; float: left;\">\n            <b>COMMENTS / SHIPPING INSTRUCTIONS:</b><br>\n            {% if doc.ifw_online_order_comments %}\n                {{ doc.ifw_online_order_comments }}\n            {% endif %}\n        </div>\n    </div>\n    <div style=\"width: 100%; float: left; margin-top: 15px;\">\n        <div style=\"width: 50%; float: left;\">\n            <b>Contact:</b><br>\n            {% if doc.contact_person %}\n                {% set email = frappe.db.get_value('Contact', doc.contact_person, \"email_id\") %}\n                {% if email %}\n                    {{email}} <br>\n                {% endif %}\n                {% set phone = frappe.db.get_value('Contact', doc.contact_person, \"phone\") %}\n                {% if phone %}\n                    {{phone}}\n                {% endif %}\n            {% elif doc.customer_address %}\n                {% set address = frappe.get_doc('Address', doc.customer_address) %}\n                {% if address.email_id %}\n                    {{address.email_id}} <br>\n                {% endif %}\n                {% if address.phone %}\n                    {{address.phone}}\n                {% endif %}\n            {% endif%}\n        </div>\n    </div>\n    <div style=\"width: 100%; float: left;\">\n        <table class=\"table table-condensed cart no-border\" style=\"font-size:100%;margin-top: 10px; height: 100%\">\n        \t<colgroup>\n        \t\t<col style=\"width:17%; height: auto;\">\n        \t\t<col style=\"width:45%\">\n        \t\t<col style=\"width:8%\">\n        \t\t<col style=\"width:40%\">\n        \t</colgroup>\n        \n        \t<tr>\n        \t\t<th class =\"text-center\" style = \"border-top:1px solid #D3D3D3;border-left:1px solid #D3D3D3!important;border-right:1px solid #D3D3D3!important;border-bottom:1px solid #D3D3D3!important;padding:1px!important;\">SKU</th>\n        \t\t<th class =\"text-center\" style = \"border-top:1px solid #D3D3D3;border-left:1px solid #D3D3D3!important;border-right:1px solid #D3D3D3!important;border-bottom:1px solid #D3D3D3!important;padding:1px!important;\">Item Name</th>\n        \t\t<th class =\"text-center\" style = \"border-top:1px solid #D3D3D3;border-left:1px solid #D3D3D3!important;border-right:1px solid #D3D3D3!important;border-bottom:1px solid #D3D3D3!important;padding:1px!important;\">Qty</th>\n        \t\t<th class =\"text-center\" style = \"border:1px solid #D3D3D3 !important;padding:0px!important;\">\n        \t\t    Price\n        \t\t    <div style=\"width: 100%; float: left:\">\n        \t\t        <div style=\"width: 50%; float: left; border-top: solid 1px #D3D3D3; border-right: solid 1px #D3D3D3;\">Unit</div>\n        \t\t        <div style=\"width: 50%; float: left; border-top: solid 1px #D3D3D3;\">Extension</div>\n        \t\t    </div>\n        \t\t</th>\n        \t</tr>\n        \n        \t{% for item in doc.items %}\n        \t<tr style=\"height: 100%;\">\n        \t\t<td class =\"text-center\" style = \"border-top:1px solid!important;border-left:1px solid #D3D3D3!important;border-right:1px solid #D3D3D3!important;border-bottom:1px solid #D3D3D3!important;padding:1px!important;\">\n        \t        {% if item.ifw_retailskusuffix %}\n        \t            {{ item.ifw_retailskusuffix }}\n        \t        {% endif %}\n        \t    </td>\n        \t\t<td style = \"border-top:1px solid!important;border-left:1px solid #D3D3D3!important;border-right:1px solid #D3D3D3!important;border-bottom:1px solid #D3D3D3!important;padding:1px!important;\"> \n        \t\t\t{{ item.item_name }}\n        \t\t</td>\n        \t\t<td class =\"text-center\" style = \"border-top:1px solid!important;border-left:1px solid #D3D3D3!important;border-right:1px solid #D3D3D3!important;border-bottom:1px solid #D3D3D3!important;padding:1px!important;\"> \n        \t\t\t{{ item.qty }} \n        \t\t</td>\n        \t\t<td class =\"text-center fix-height\" style =\"border:1px solid #D3D3D3!important;padding:0px!important; height: 100%\">\n        \t\t    <div style=\"width: 50%; float: left; border-right: solid 1px #D3D3D3; height: 100%;\">\n        \t\t        {{ item.get_formatted(\"rate\") }}\n        \t\t    </div>\n        \t\t    <div style=\"width: 50%; float: left; height: 100%;\">\n        \t\t        {{ item.get_formatted(\"amount\") }}\n        \t\t    </div>\n        \t\t</td>\n        \t\t\n        \t</tr>\n        \n        \n        \t{% endfor %}\n        </table>\n    </div>\n    <div style=\"width: 100%; float: left;\">\n        <div style=\"width: 50%; float: left;\">\n            <b>* ALL PRICES IN {{doc.currency}}</b>\n        </div>\n        <div style=\"width: 50%; float: left;\">\n            <div style=\"border: solid 1px #dfe2e5; padding: 10px 0px; width: 100%;\">\n                <table style=\"width: 100%;\">\n                    <tr>\n                        <td style=\"width: 50%; text-align: right;\"><b>SUBTOTAL</b></td>\n                        <td style=\"width: 50%;\"><b>{{doc.get_formatted(\"total\")}}</b></td>\n                    </tr>\n                    {% for tax in doc.taxes %}\n                        <tr>\n                            <td style=\"width: 50%; text-align: right;\"><b>{{ tax.description }}</b></td>\n                            <td style=\"width: 50%;\"><b>{{ tax.get_formatted(\"tax_amount\") }}</b></td>\n                        </tr>\n                    {% endfor %}\n                    <tr>\n                        <td style=\"width: 50%; text-align: right;\"><b>TOTAL</b></td>\n                        <td style=\"width: 50%;\"><b>{{doc.get_formatted(\"grand_total\")}}</b></td>\n                    </tr>\n                </table>\n            </div>\n        </div>\n    </div>\n</div>\n<div id=\"footer-html\">\n    \t{% if doc.terms %}\n    \t    <div id=\"footer-html\" class=\"visible-pdf\" style=\"display: block !important; order: 1; margin-top: auto;\">\n\t\t        <span style=\"font-size: 8px !important; text-align: center !important;\">{{doc.terms}}</span>\n\t        </div>\n        {% endif %}\n    </div>",
 "idx": 0,
 "line_breaks": 0,
 "modified": "2021-12-22 03:37:48.042615",
 "modified_by": "Administrator",
 "module": "Metactical",
 "name": "SO - Custom V1",
 "owner": "Administrator",
 "print_format_builder": 0,
 "print_format_type": "Jinja",
 "raw_printing": 0,
 "show_section_headings": 0,
 "standard": "Yes"
}
